systems/__init__.py
systems/algos.py
systems/errors.py
systems/format.py
systems/lexer.py
systems/models.py
systems/parse.py
systems/systems.py
systems/viz.py
systems-0.1.0.data/scripts/systems-fmt
systems-0.1.0.data/scripts/systems-lex
systems-0.1.0.data/scripts/systems-run
systems-0.1.0.data/scripts/systems-viz
systems-0.1.0.dist-info/METADATA
systems-0.1.0.dist-info/RECORD
systems-0.1.0.dist-info/WHEEL
systems-0.1.0.dist-info/top_level.txt
