Metadata-Version: 2.1
Name: systems
Version: 0.1.0
Summary: Describe and run systems diagrams.
Home-page: https://github.com/lethain/systems
Author: Will Larson
Author-email: lethain@gmail.com
License: UNKNOWN
Platform: UNKNOWN
Classifier: Programming Language :: Python :: 3
Classifier: License :: OSI Approved :: MIT License
Classifier: Operating System :: OS Independent
Requires-Dist: graphviz
